LICENSE
setup.cfg
setup.py
glove/__init__.py
glove/corpus.py
glove/corpus_cython.cpp
glove/glove.py
glove/glove_cython.c
glove/metrics/__init__.py
glove/metrics/accuracy.py
glove/metrics/accuracy_cython.c
glove_python3.egg-info/PKG-INFO
glove_python3.egg-info/SOURCES.txt
glove_python3.egg-info/dependency_links.txt
glove_python3.egg-info/requires.txt
glove_python3.egg-info/top_level.txt
tests/test_corpus.py
tests/test_glove.py