Metadata-Version: 2.1
Name: glove-python3
Version: 0.1.0
Summary: Python implementation of Global Vectors for Word Representation (GloVe)
Home-page: https://github.com/maciejkula/glove-python
Download-URL: https://github.com/maciejkula/glove-python/tarball/0.1.0
Author: Maciej Kula
License: Apache 2.0
Classifier: Development Status :: 3 - Alpha
Classifier: License :: OSI Approved :: Apache Software License
Classifier: Topic :: Scientific/Engineering :: Artificial Intelligence
License-File: LICENSE
